topaz/__init__.py
topaz/_version.py
topaz/algorithms.py
topaz/cuda.py
topaz/denoise.py
topaz/extract.py
topaz/filters.py
topaz/main.py
topaz/methods.py
topaz/metrics.py
topaz/mrc.py
topaz/predict.py
topaz/stats.py
topaz/torch.py
topaz/training.py
topaz/commands/__init__.py
topaz/commands/boxes_to_coordinates.py
topaz/commands/convert.py
topaz/commands/coordinates_to_boxes.py
topaz/commands/coordinates_to_eman2_json.py
topaz/commands/coordinates_to_star.py
topaz/commands/denoise.py
topaz/commands/denoise3d.py
topaz/commands/downsample.py
topaz/commands/extract.py
topaz/commands/gui.py
topaz/commands/normalize.py
topaz/commands/particle_stack.py
topaz/commands/precision_recall_curve.py
topaz/commands/preprocess.py
topaz/commands/scale_coordinates.py
topaz/commands/segment.py
topaz/commands/split.py
topaz/commands/star_particles_threshold.py
topaz/commands/star_to_coordinates.py
topaz/commands/train.py
topaz/commands/train_test_split.py
topaz/denoising/__init__.py
topaz/denoising/datasets.py
topaz/denoising/models.py
topaz/gui/topaz.html
topaz/model/__init__.py
topaz/model/classifier.py
topaz/model/factory.py
topaz/model/generative.py
topaz/model/utils.py
topaz/model/features/__init__.py
topaz/model/features/basic.py
topaz/model/features/densenet.py
topaz/model/features/msnet.py
topaz/model/features/resnet.py
topaz/pretrained/denoise/affine_L1_v0.2.2.sav
topaz/pretrained/denoise/fcnn_L1_v0.2.2.sav
topaz/pretrained/denoise/unet-3d-10a-v0.2.4.sav
topaz/pretrained/denoise/unet-3d-20a-v0.2.4.sav
topaz/pretrained/denoise/unet_L2_v0.2.1.sav
topaz/pretrained/denoise/unet_L2_v0.2.2.sav
topaz/pretrained/denoise/unet_small_L1_v0.2.2.sav
topaz/pretrained/detector/resnet16_u32.sav
topaz/pretrained/detector/resnet16_u64.sav
topaz/pretrained/detector/resnet8_u32.sav
topaz/pretrained/detector/resnet8_u64.sav
topaz/transform/__init__.py
topaz/transform/scaled_gaussian_mixture.py
topaz/utils/__init__.py
topaz/utils/conversions.py
topaz/utils/files.py
topaz/utils/image.py
topaz_em-0.3.17.dist-info/licenses/LICENSE
topaz_em-0.3.17.dist-info/METADATA
topaz_em-0.3.17.dist-info/WHEEL
topaz_em-0.3.17.dist-info/entry_points.txt
topaz_em-0.3.17.dist-info/top_level.txt
topaz_em-0.3.17.dist-info/RECORD
