Metadata-Version: 2.4
Name: topaz-em
Version: 0.3.17
Summary: Particle picking with positive-unlabeled CNNs
Home-page: https://github.com/tbepler/topaz
Author: Tristan Bepler
Author-email: Tristan Bepler <tbepler@mit.edu>
License: GPLv3
Project-URL: Homepage, https://github.com/tbepler/topaz
Keywords: cryoEM,particle-picking,CNN,positive-unlabeled,denoise,topaz
Classifier: License :: OSI Approved :: GNU General Public License v3 (GPLv3)
Classifier: Programming Language :: Python :: 3
Classifier: Programming Language :: Python :: 3.8
Classifier: Programming Language :: Python :: 3.9
Classifier: Programming Language :: Python :: 3.10
Classifier: Programming Language :: Python :: 3.11
Classifier: Programming Language :: Python :: 3.12
Requires-Python: >=3.8,<=3.13
License-File: LICENSE
Requires-Dist: torch>=1.0.0
Requires-Dist: torchvision
Requires-Dist: tqdm>=4.65.0
Requires-Dist: h5py>=3.7.0
Requires-Dist: numpy>=1.11
Requires-Dist: pandas>=0.20.3
Requires-Dist: scikit-learn>=0.19.0
Requires-Dist: scipy>=0.17.0
Requires-Dist: pillow>=6.2.0
Requires-Dist: future
Dynamic: author
Dynamic: home-page
Dynamic: license-file
Dynamic: requires-python
